{
  "title": "Bangkok Thai",
  "tags": [
    "Vegetarian-Friendly"
  ],
  "typeOfFood": "\n                                        Ovo, Thai, Take-out, Non-veg\n                                    ",
  "description": "Serves meat, veg options available. Thai food restaurant. Ask to substitute tofu for meat and say no egg or fish sauce. Staff is willing to accommodate.",
  "priceRange": "Inexpensive",
  "streetAddress": "4624 34th St",
  "postalCode": "79410",
  "phone": "tel:806-791-7787",
  "venueHours": "\n                                                                                                            \n                                                                                                        Mon-Sat 11:00am-9:00pm\n                                                ",
  "listingFeatures": [
    "Accepts credit cards"
  ],
  "gmaps": "http://maps.googleapis.com/maps/api/staticmap?center=33.563662,-101.910088&zoom=15&size=458x118&maptype=roadmap&markers=icon:http%3A%2F%2Fgoo.gl%2F1RDrbh%7Cshadow:true%7C33.563662,-101.910088&sensor=false&key=AIzaSyBrIo4v01Yet3zb6VunVdenxRtXWFnwfxk"
}