{
  "title": "Bio c' Bon",
  "tags": [
    "Health Food Store"
  ],
  "description": "Organic and natural food grocery store.",
  "streetAddress": "670 avenue du Canton Vert",
  "postalCode": "13190",
  "phone": "tel:0496218101",
  "venueHours": "\n                                                                                                        Mon-Sat 9:00am-7:30pm, Sun 9:30am-1:00pm\n                                                ",
  "listingFeatures": [],
  "gmaps": "http://maps.googleapis.com/maps/api/staticmap?center=43.342053,5.472083&zoom=15&size=458x118&maptype=roadmap&markers=icon:http%3A%2F%2Fgoo.gl%2F1RDrbh%7Cshadow:true%7C43.342053,5.472083&sensor=false&key=AIzaSyBrIo4v01Yet3zb6VunVdenxRtXWFnwfxk"
}