{
  "title": "Circolo ARCI L'Alba ",
  "tags": [
    "Vegetarian-Friendly"
  ],
  "typeOfFood": "\n                                        Lacto, Ovo, Italian, Organic, Non-veg\n                                    ",
  "description": "Serves meat, veg options available. Restaurant run by an association that takes care of psycho-social rehabilitation. Most of working members come from psychological distress experiences. From Wed to Sun serves vegetarian and vegan  dinners. From Mon to Fri for lunch serves only traditional Italian and Tuscan dishes.",
  "priceRange": "Moderate",
  "streetAddress": "Via delle Belle Torri, 8",
  "postalCode": "56100",
  "phone": "tel:+39-050544211",
  "venueHours": "\n                                                                                                        Mon-Tue 9:00am-7:00pm, Wed-Fri 9:00am-12:00am, Sat 2:00pm-12:00am, Sun 4:00pm-12:00am\n                                                ",
  "listingFeatures": [],
  "fb": "http://www.facebook.com/pages/Associazione-LAlba/125727901995",
  "gmaps": "http://maps.googleapis.com/maps/api/staticmap?center=43.715684,10.405386&zoom=15&size=458x118&maptype=roadmap&markers=icon:http%3A%2F%2Fgoo.gl%2F1RDrbh%7Cshadow:true%7C43.715684,10.405386&sensor=false&key=AIzaSyBrIo4v01Yet3zb6VunVdenxRtXWFnwfxk"
}