{
  "title": "Down the Alley Cafe",
  "tags": [
    "Vegetarian-Friendly"
  ],
  "typeOfFood": "\n                                        Lacto, Ovo, American, Organic, Take-out, Bakery, Non-veg\n                                    ",
  "description": "Serves meat, veg options available. Country-style cafe offering organic food with salads, sandwiches, wraps, quesadilla, burgers, and soups; plenty of side add-ons. Uses cheese in most items - ask to omit.",
  "priceRange": "Moderate",
  "streetAddress": "603 W Main St",
  "postalCode": "76234",
  "phone": "tel:940-627-0235",
  "venueHours": "\n                                                                                                            \n                                                                                                        Mon-Fri 11:00am-2:00pm\n                                                ",
  "listingFeatures": [
    "Outdoor seating",
    "Accepts credit cards"
  ],
  "fb": "http://www.facebook.com/pages/Down-The-Alley-Cafe/101464449924072",
  "gmaps": "http://maps.googleapis.com/maps/api/staticmap?center=33.233679,-97.591671&zoom=15&size=458x118&maptype=roadmap&markers=icon:http%3A%2F%2Fgoo.gl%2F1RDrbh%7Cshadow:true%7C33.233679,-97.591671&sensor=false&key=AIzaSyBrIo4v01Yet3zb6VunVdenxRtXWFnwfxk"
}