{
  "title": "extraVEGANza Pgh",
  "tags": [
    "Vegan Restaurant"
  ],
  "typeOfFood": "\n                                        Vegan, American, Organic, Raw, Juice bar, Take-out, Catering, Fusion\n                                    ",
  "description": "Inside Schwartz Market you will find this vegan, gluten-free cafe and juice bar offering items such as grilled carrot hotdogs on anti-wheat seed-grain bun, raw pizza on dehydrated whole grain-seed crust, open-face roasted veggie sandwich, raw zucchini lasagna, raw soup, raw cinnamon buns, and raw cacao walnut brownies. Here since spring 2015.",
  "priceRange": "Moderate",
  "streetAddress": "1317 E Carson St",
  "postalCode": "15203",
  "phone": "tel:412-212-8816",
  "venueHours": "\n                                                                                                            \n                                                                                                        Tue-Sat 11:00am-4:00pm, 6:00pm-8:30pm\n                                                ",
  "listingFeatures": [
    "Wheelchair accessible",
    "Accepts credit cards"
  ],
  "fb": "http://www.facebook.com/zestwishes",
  "gmaps": "http://maps.googleapis.com/maps/api/staticmap?center=40.428843,-79.984610&zoom=15&size=458x118&maptype=roadmap&markers=icon:http%3A%2F%2Fgoo.gl%2F1RDrbh%7Cshadow:true%7C40.428843,-79.984610&sensor=false&key=AIzaSyBrIo4v01Yet3zb6VunVdenxRtXWFnwfxk"
}