{
  "title": "GNJ Vegetarian Bistro",
  "tags": [
    "Vegetarian Restaurant"
  ],
  "typeOfFood": "\n                                        Lacto, Indian, International, Western, Canadian\n                                    ",
  "description": "A casual vegetarian restaurant est. 2014. On the menu are a mix variety of cuisines from Indian to Italian: poutine, sandwiches and wraps, pasta, salad, veggie bowls. Uses dairy, so vegans should ask which dishes are suitable.",
  "priceRange": "Moderate",
  "streetAddress": "100 - 7310 120th St",
  "postalCode": "V3W 3M9",
  "phone": "tel:778-565-2020",
  "venueHours": "\n                                                                                                            \n                                                                                                        Mon 12:00pm-8:00pm, Tue-Thu 11:00am-9:00pm, Fri-Sat 11:00am-10:00pm, Sun 11:00am-9:00pm\n                                                ",
  "listingFeatures": [
    "Wheelchair accessible",
    "Accepts credit cards"
  ],
  "fb": "http://www.facebook.com/GNJVegetarianBistro",
  "gmaps": "http://maps.googleapis.com/maps/api/staticmap?center=49.134933,-122.890244&zoom=15&size=458x118&maptype=roadmap&markers=icon:http%3A%2F%2Fgoo.gl%2F1RDrbh%7Cshadow:true%7C49.134933,-122.890244&sensor=false&key=AIzaSyBrIo4v01Yet3zb6VunVdenxRtXWFnwfxk"
}