{
  "title": "Ile de Elequa - maybe closed",
  "tags": [
    "Vegetarian-Friendly"
  ],
  "typeOfFood": "\n                                        Organic, Western, Spanish, Non-veg\n                                    ",
  "description": "Serves meat, veg options available. Feb 2013 reported by happycow member no longer pure veg, and most dishes now contain meat or fish. Organic restaurant offering menu-del-dia and other dishes like lasagna, quiche, Colombian tamale. Space designed to the standards of feng shui. Previously operated as Kimpira. JAN 2014 NOTE: maybe closed/shut down, please verify and let HappyCow know.",
  "priceRange": "Moderate",
  "streetAddress": "C/ Juristas, 12",
  "postalCode": "46001",
  "phone": "tel:963923422",
  "venueHours": "\n                                                                                                            \n                                                                                                        Mon-Sun 1:30pm-4:00pm, Sat 8:30pm-12:00am\n                                                ",
  "listingFeatures": [
    "Accepts credit cards"
  ],
  "gmaps": "http://maps.googleapis.com/maps/api/staticmap?center=39.475968,-0.376646&zoom=15&size=458x118&maptype=roadmap&markers=icon:http%3A%2F%2Fgoo.gl%2F1RDrbh%7Cshadow:true%7C39.475968,-0.376646&sensor=false&key=AIzaSyBrIo4v01Yet3zb6VunVdenxRtXWFnwfxk"
}