{
  "title": "Mandala",
  "tags": [
    "Vegetarian Restaurant"
  ],
  "typeOfFood": "\n                                        Lacto, Ovo, Pizza, Organic, Western, Juice bar, Beer/Wine, Take-out\n                                    ",
  "description": "Opened Feb 2014 a health food cafe offering wraps, sandwiches, vegetarian burgers, pizza, salads, juices and smoothies. Ask for menu of the day. Has gluten-free.",
  "priceRange": "Moderate",
  "streetAddress": "Plaza Vita, Local 14",
  "phone": "tel:+506-2289-3989",
  "venueHours": "\n                                                                                                            \n                                                                                                        Mon-Sun 12:00pm-10:00pm\n                                                ",
  "listingFeatures": [
    "Outdoor seating",
    "Accepts credit cards"
  ],
  "fb": "http://www.facebook.com/mandalacostarica",
  "gmaps": "http://maps.googleapis.com/maps/api/staticmap?center=9.930883,-84.138899&zoom=15&size=458x118&maptype=roadmap&markers=icon:http%3A%2F%2Fgoo.gl%2F1RDrbh%7Cshadow:true%7C9.930883,-84.138899&sensor=false&key=AIzaSyBrIo4v01Yet3zb6VunVdenxRtXWFnwfxk"
}