{
  "title": "Mercearia Bio",
  "tags": [
    "Health Food Store"
  ],
  "description": "An all organic food store with organic coffee shop service, by the riverside in Portimao. Online store with home deliveries nationwide (Portugal). Their organic product range includes fresh fruit and vegetables, cereals, pastas, juices, leguminous plants, snacks, tofu, seitan, jams, teas, coffees, wines, among other organic food products. Moved to this new space from Rua 25 de Abril in Apr 2014.",
  "streetAddress": "Rua das Comunicações, Edificio Casa do Rio Loja C",
  "postalCode": "8500-657",
  "phone": "tel:282-476-439",
  "venueHours": "\n                                                                                                        Mon 10:00am-7:00pm, Tue-Fri 9:00am-7:00pm, Sat 9:00am-1:00pm\n                                                ",
  "listingFeatures": [],
  "gmaps": "http://maps.googleapis.com/maps/api/staticmap?center=37.135979,-8.535607&zoom=15&size=458x118&maptype=roadmap&markers=icon:http%3A%2F%2Fgoo.gl%2F1RDrbh%7Cshadow:true%7C37.135979,-8.535607&sensor=false&key=AIzaSyBrIo4v01Yet3zb6VunVdenxRtXWFnwfxk"
}