{
  "title": "My Family's Pizza",
  "tags": [
    "Vegetarian-Friendly"
  ],
  "typeOfFood": "\n                                        Vegan-friendly, Lacto, Pizza, Italian, Fast food, Delivery, Take-out, Non-veg\n                                    ",
  "description": "Serves meat, veg options available. Pizzeria chain in Dallas area offering vegan faux meat toppings like soyrizo, bacon, cheese, ground beef, pepperoni, sausage, chicken. Some locations also offer a vegan chicken parmesan dish. Formerly known as Pizza by Marco (same company).",
  "priceRange": "Moderate",
  "streetAddress": "5960 W Parker Rd Ste 286",
  "postalCode": "75093",
  "phone": "tel:972-378-4085",
  "venueHours": "\n                                                                                                            \n                                                                                                        Call for hours - tell us\n                                                ",
  "listingFeatures": [],
  "gmaps": "http://maps.googleapis.com/maps/api/staticmap?center=33.044878,-96.827981&zoom=15&size=458x118&maptype=roadmap&markers=icon:http%3A%2F%2Fgoo.gl%2F1RDrbh%7Cshadow:true%7C33.044878,-96.827981&sensor=false&key=AIzaSyBrIo4v01Yet3zb6VunVdenxRtXWFnwfxk"
}