{
  "title": "Probio",
  "tags": [
    "Health Food Store"
  ],
  "description": "Carries organic and non organic vegan dry food items, refrigerated vegan items like tofu, veggie meats, soy yogurt, soy spread and more. Good selection of gluten free products. Large selection of tea and herbs. Also carries organic and eco-friendly cosmetics and cleaning products. ",
  "streetAddress": "Radlinskeho c 1",
  "postalCode": "94901",
  "phone": "tel:037-6526835",
  "venueHours": "\n                                                                                                            \n                                                                                                        Call for hours - tell us\n                                                ",
  "listingFeatures": [],
  "gmaps": "http://maps.googleapis.com/maps/api/staticmap?center=48.312305,18.087944&zoom=15&size=458x118&maptype=roadmap&markers=icon:http%3A%2F%2Fgoo.gl%2F1RDrbh%7Cshadow:true%7C48.312305,18.087944&sensor=false&key=AIzaSyBrIo4v01Yet3zb6VunVdenxRtXWFnwfxk"
}