{
  "title": "Progetto Vivere Vegan ONLUS",
  "tags": [
    "Veg Organization",
    "Vegan"
  ],
  "description": "Florence vegan association.",
  "streetAddress": "via di Montisoni, 37, Bagno a Ripoli",
  "postalCode": "50012",
  "phone": "tel:055-620262",
  "listingFeatures": [],
  "gmaps": "http://maps.googleapis.com/maps/api/staticmap?center=43.720917,11.340026&zoom=15&size=458x118&maptype=roadmap&markers=icon:http%3A%2F%2Fgoo.gl%2F1RDrbh%7Cshadow:true%7C43.720917,11.340026&sensor=false&key=AIzaSyBrIo4v01Yet3zb6VunVdenxRtXWFnwfxk"
}