{
  "title": "Legumbres Mayas",
  "tags": [
    "Vegetarian Restaurant"
  ],
  "typeOfFood": "\n                                        Vegan-friendly, Lacto, Ovo, Pizza, Guatemala, Latin American\n                                    ",
  "description": "Vegetarian restaurant on Flores island serving a mix of local (e.g. Guatemalan beans and rice) and international (e.g. pizza) dishes. Simple decor.",
  "priceRange": "Inexpensive",
  "streetAddress": "Calle 15 de Septiembre",
  "phone": "tel:43247259",
  "venueHours": "\n                                                                                                            \n                                                                                                        Mon-Fri 8:00am-9:00pm, Sat 8:00am-5:00pm\n                                                ",
  "listingFeatures": [
    "Cash only"
  ],
  "fb": "http://www.facebook.com/Restaurante-Legumbres-Mayas-959585034096209",
  "gmaps": "http://maps.googleapis.com/maps/api/staticmap?center=16.928994,-89.891518&zoom=15&size=458x118&maptype=roadmap&markers=icon:http%3A%2F%2Fgoo.gl%2F1RDrbh%7Cshadow:true%7C16.928994,-89.891518&sensor=false&key=AIzaSyBrIo4v01Yet3zb6VunVdenxRtXWFnwfxk"
}