{
  "title": "Rest'o",
  "tags": [
    "Vegetarian Restaurant"
  ],
  "typeOfFood": "\n                                        Vegan-friendly, Lacto, Organic, Beer/Wine, Fusion\n                                    ",
  "description": "A fully organic bio vegetarian restaurant with gluten free and vegan options. All food made-in-house to order. Reservations required on Friday nights. Confirmed open, Aug 2015 - although front door still shows name of previous restaurant (Kfee).",
  "priceRange": "Moderate",
  "streetAddress": "16 Quai de Bacalan",
  "phone": "tel:0532080193",
  "venueHours": "\n                                                                                                            \n                                                                                                        Tue-Fri 12:00pm-2:30pm, Fri 8:00pm-10:30pm, Sat 8:30pm-10:00pm\n                                                ",
  "listingFeatures": [
    "Accepts credit cards"
  ],
  "fb": "http://www.facebook.com/pages/RestO/1504278026475171",
  "gmaps": "http://maps.googleapis.com/maps/api/staticmap?center=44.857374,-0.560460&zoom=15&size=458x118&maptype=roadmap&markers=icon:http%3A%2F%2Fgoo.gl%2F1RDrbh%7Cshadow:true%7C44.857374,-0.560460&sensor=false&key=AIzaSyBrIo4v01Yet3zb6VunVdenxRtXWFnwfxk"
}