{
  "title": "Routine",
  "tags": [
    "Vegetarian Restaurant"
  ],
  "typeOfFood": "\n                                        Vegan-friendly, Lacto, Ovo, American, Organic, Beer/Wine, Take-out, Bakery, Fusion\n                                    ",
  "description": "Coffee house and vegetarian eatery in Bushwick, opened since Oct 2015. Serves Toby's Estate coffee and dishes like avocado toast, breakfast burrito, bahn mi, and burgers. Makes hand pies and baked goods onsite. Brunch and vegan donuts is served on the weekend.",
  "priceRange": "Moderate",
  "streetAddress": "631 Wilson Ave",
  "postalCode": "11207",
  "phone": "tel:347-787-0546",
  "venueHours": "\n                                                                                                        Mon-Fri 7:00am-8:00pm, Sat 8:00am-8:00pm, Sun 8:00am-6:00pm\n                                                ",
  "listingFeatures": [
    "Accepts credit cards"
  ],
  "fb": "http://www.facebook.com/RoutineBushwick",
  "gmaps": "http://maps.googleapis.com/maps/api/staticmap?center=40.689767,-73.906008&zoom=15&size=458x118&maptype=roadmap&markers=icon:http%3A%2F%2Fgoo.gl%2F1RDrbh%7Cshadow:true%7C40.689767,-73.906008&sensor=false&key=AIzaSyBrIo4v01Yet3zb6VunVdenxRtXWFnwfxk"
}