{
  "title": "Seward Community Co-op",
  "tags": [
    "Health Food Store"
  ],
  "description": "Twin Cities' co-op market, established since 1972, originally at corner of 22nd and Franklin. Offers fresh organic produce, deli food, nutritional vitamins and supplements, natural groceries.",
  "streetAddress": "2823 E Franklin Ave",
  "postalCode": "55406",
  "phone": "tel:612-338-2465",
  "venueHours": "\n                                                                                                            \n                                                                                                        Call for hours - tell us\n                                                ",
  "listingFeatures": [],
  "gmaps": "http://maps.googleapis.com/maps/api/staticmap?center=44.962750,-93.231044&zoom=15&size=458x118&maptype=roadmap&markers=icon:http%3A%2F%2Fgoo.gl%2F1RDrbh%7Cshadow:true%7C44.962750,-93.231044&sensor=false&key=AIzaSyBrIo4v01Yet3zb6VunVdenxRtXWFnwfxk"
}