{
  "title": "Sisters 2",
  "tags": [
    "Vegetarian-Friendly"
  ],
  "typeOfFood": "\n                                        Lacto, Ovo, Western, Non-veg\n                                    ",
  "description": "Serves meat, veg options available. In a small town with little vegetarian food, this cafe and bakery is a good option as it is clean and cheerful and the owner, who speaks English, will accommodate veg requests. Serves breakfast and baked goods, pumpkin pancake, coffee, tea, fruit smoothies. Free Wi-Fi. Directions: No street names or numbers, just go towards the river at the 2000 monument, and it's on the left hand side of the road.",
  "priceRange": "Moderate",
  "streetAddress": "On the road from the 2000 statue, towards the riverfront",
  "phone": "tel:017777470",
  "venueHours": "\n                                                                                                            \n                                                                                                        Call for hours - tell us\n                                                ",
  "listingFeatures": [],
  "gmaps": "http://maps.googleapis.com/maps/api/staticmap?center=10.604689,104.175657&zoom=15&size=458x118&maptype=roadmap&markers=icon:http%3A%2F%2Fgoo.gl%2F1RDrbh%7Cshadow:true%7C10.604689,104.175657&sensor=false&key=AIzaSyBrIo4v01Yet3zb6VunVdenxRtXWFnwfxk"
}