{
  "title": "Sivertsens Kafe",
  "tags": [
    "Vegan Restaurant"
  ],
  "typeOfFood": "\n                                        Vegan, Western, Juice bar, Beer/Wine, Norwegian\n                                    ",
  "description": "Small vegetarian cafe that hosts live music. Offers only one daily menu with two dishes and a cake. The owner is the waitress, cook, and barkeeper in one person. Closes July.",
  "priceRange": "Moderate",
  "streetAddress": "Vestregata 48",
  "phone": "tel:+47-77655434",
  "venueHours": "\n                                                                                                            \n                                                                                                        Tue-Thu 3:00pm-1:30am, Fri 3:00pm-3:30am, Sat 12:00pm-3:30am, Sun 3:00pm-1:30am\n                                                ",
  "listingFeatures": [],
  "gmaps": "http://maps.googleapis.com/maps/api/staticmap?center=69.651756,18.954765&zoom=15&size=458x118&maptype=roadmap&markers=icon:http%3A%2F%2Fgoo.gl%2F1RDrbh%7Cshadow:true%7C69.651756,18.954765&sensor=false&key=AIzaSyBrIo4v01Yet3zb6VunVdenxRtXWFnwfxk"
}