{
  "title": "Thai Palace",
  "tags": [
    "Vegetarian-Friendly"
  ],
  "typeOfFood": "\n                                        Vegan-friendly, Lacto, Ovo, Thai, Beer/Wine, Take-out, Non-veg\n                                    ",
  "description": "Serves meat, veg options available. Thai food restaurant, has a separate vegetarian menu section. Try the pad thai.",
  "priceRange": "Inexpensive",
  "streetAddress": "3262 J St",
  "postalCode": "95816",
  "phone": "tel:916-447-5353",
  "venueHours": "\n                                                                                                            \n                                                                                                        Call for hours - tell us\n                                                ",
  "listingFeatures": [
    "Accepts credit cards"
  ],
  "gmaps": "http://maps.googleapis.com/maps/api/staticmap?center=38.571863,-121.462536&zoom=15&size=458x118&maptype=roadmap&markers=icon:http%3A%2F%2Fgoo.gl%2F1RDrbh%7Cshadow:true%7C38.571863,-121.462536&sensor=false&key=AIzaSyBrIo4v01Yet3zb6VunVdenxRtXWFnwfxk"
}