{
  "title": "Tsai Siang Geng",
  "tags": [
    "Vegetarian Restaurant"
  ],
  "typeOfFood": "\n                                        Vegan-friendly, Ovo, Taiwanese\n                                    ",
  "description": "Little healthy food vegetarian restaurant. Varied and simplified menu (in Chinese) includes hot rice bowls, noodles, and hot pots. Many items made in-house, including dumplings (good in hot and sour soup) and red chili pepper sauce. Has a retail section.",
  "priceRange": "Moderate",
  "streetAddress": "274, Sec. 1, Heping East Road, Da-an District",
  "phone": "tel:02-33653077",
  "venueHours": "\n                                                                                                            \n                                                                                                        Call for hours - tell us\n                                                ",
  "listingFeatures": [
    "Wheelchair accessible"
  ],
  "gmaps": "http://maps.googleapis.com/maps/api/staticmap?center=25.026040,121.532607&zoom=15&size=458x118&maptype=roadmap&markers=icon:http%3A%2F%2Fgoo.gl%2F1RDrbh%7Cshadow:true%7C25.026040,121.532607&sensor=false&key=AIzaSyBrIo4v01Yet3zb6VunVdenxRtXWFnwfxk"
}