{
  "title": "Yamal Asham",
  "tags": [
    "Vegetarian-Friendly"
  ],
  "typeOfFood": "\n                                        Juice bar, Take-out, Middle Eastern, Syrian, Non-veg\n                                    ",
  "description": "Serves meat, veg options available. A Syrian restaurant offers some vegan and vegetarian choices like lentil soup, veggie salad, falafel, hummus, as well as fruit desserts and juices. Located close to the city center, 5-10 minutes walk from Medina.",
  "priceRange": "Inexpensive",
  "streetAddress": "5 Rue Al Maghrib Al Arabi",
  "phone": "tel:05-37720276/,%2006-7901010",
  "venueHours": "\n                                                                                                            \n                                                                                                        Call for hours - tell us\n                                                ",
  "listingFeatures": [],
  "fb": "http://www.facebook.com/yamalalcham",
  "gmaps": "http://maps.googleapis.com/maps/api/staticmap?center=33.971590,-6.849813&zoom=15&size=458x118&maptype=roadmap&markers=icon:http%3A%2F%2Fgoo.gl%2F1RDrbh%7Cshadow:true%7C33.971590,-6.849813&sensor=false&key=AIzaSyBrIo4v01Yet3zb6VunVdenxRtXWFnwfxk"
}